README.md
setup.cfg
setup.py
jcp_distributions/Binomialdistribution.py
jcp_distributions/Gaussiandistribution.py
jcp_distributions/Generaldistribution.py
jcp_distributions/__init__.py
jcp_distributions.egg-info/PKG-INFO
jcp_distributions.egg-info/SOURCES.txt
jcp_distributions.egg-info/dependency_links.txt
jcp_distributions.egg-info/not-zip-safe
jcp_distributions.egg-info/top_level.txt